odoo8_addon_web_recipients_uncheck-8.0.0.3.0-py2.7-nspkg.pth
odoo_addons/web_recipients_uncheck/__openerp__.py
odoo_addons/web_recipients_uncheck/__init__.py
odoo_addons/web_recipients_uncheck/README.rst
odoo_addons/web_recipients_uncheck/view/web_recipients_uncheck.xml
odoo_addons/web_recipients_uncheck/i18n/web_recipients_uncheck.pot
odoo_addons/web_recipients_uncheck/static/description/icon.png
odoo_addons/web_recipients_uncheck/static/src/js/web_recipients_uncheck.js
odoo8_addon_web_recipients_uncheck-8.0.0.3.0.dist-info/top_level.txt
odoo8_addon_web_recipients_uncheck-8.0.0.3.0.dist-info/WHEEL
odoo8_addon_web_recipients_uncheck-8.0.0.3.0.dist-info/RECORD
odoo8_addon_web_recipients_uncheck-8.0.0.3.0.dist-info/metadata.json
odoo8_addon_web_recipients_uncheck-8.0.0.3.0.dist-info/DESCRIPTION.rst
odoo8_addon_web_recipients_uncheck-8.0.0.3.0.dist-info/METADATA
odoo8_addon_web_recipients_uncheck-8.0.0.3.0.dist-info/namespace_packages.txt
